llm_evaluation_framework/__init__.py
llm_evaluation_framework/auto_suggestion_engine.py
llm_evaluation_framework/cli.py
llm_evaluation_framework/model_inference_engine.py
llm_evaluation_framework/model_registry.py
llm_evaluation_framework/test_dataset_generator.py
llm_evaluation_framework/cli/__init__.py
llm_evaluation_framework/cli/__main__.py
llm_evaluation_framework/cli/main.py
llm_evaluation_framework/core/__init__.py
llm_evaluation_framework/core/base_engine.py
llm_evaluation_framework/core/base_registry.py
llm_evaluation_framework/datasets/__init__.py
llm_evaluation_framework/engines/__init__.py
llm_evaluation_framework/engines/async_inference_engine.py
llm_evaluation_framework/evaluation/__init__.py
llm_evaluation_framework/evaluation/scoring_strategies.py
llm_evaluation_framework/persistence/__init__.py
llm_evaluation_framework/persistence/db_store.py
llm_evaluation_framework/persistence/json_store.py
llm_evaluation_framework/persistence/persistence_manager.py
llm_evaluation_framework/registry/__init__.py
llm_evaluation_framework/registry/model_registry.py
llm_evaluation_framework/tests/__init__.py
llm_evaluation_framework/tests/test_cli.py
llm_evaluation_framework/utils/__init__.py
llm_evaluation_framework/utils/error_handler.py
llm_evaluation_framework/utils/logger.py
llmevaluationframework-0.0.21.dist-info/licenses/LICENSE
tests/__init__.py
tests/test_all_modules.py
tests/test_cli_comprehensive.py
tests/test_coverage_completion.py
tests/test_dataset_generator.py
tests/test_error_handler_comprehensive.py
tests/test_increase_coverage.py
tests/test_logger_comprehensive.py
tests/test_model_inference_engine_comprehensive.py
tests/test_new_modules.py
tests/test_persistence_comprehensive.py
llmevaluationframework-0.0.21.dist-info/METADATA
llmevaluationframework-0.0.21.dist-info/WHEEL
llmevaluationframework-0.0.21.dist-info/entry_points.txt
llmevaluationframework-0.0.21.dist-info/top_level.txt
llmevaluationframework-0.0.21.dist-info/RECORD
