Metadata-Version: 2.4
Name: LLMEvaluationFramework
Version: 0.0.21
Summary: Enterprise-Grade Python Framework for Large Language Model Evaluation & Testing
Home-page: https://github.com/isathish/LLMEvaluationFramework
Author: Sathishkumar Nagarajan
Author-email: mail@sathishkumarnagarajan.com
License: MIT
Project-URL: Bug Tracker, https://github.com/isathish/LLMEvaluationFramework/issues
Project-URL: Documentation, https://isathish.github.io/LLMEvaluationFramework/
Project-URL: Source, https://github.com/isathish/LLMEvaluationFramework
Keywords: llm,evaluation,testing,benchmarking,ai,ml,machine-learning,natural-language-processing,nlp,language-models,openai,gpt,anthropic,claude
Classifier: Programming Language :: Python :: 3
Classifier: Programming Language :: Python :: 3.8
Classifier: Programming Language :: Python :: 3.9
Classifier: Programming Language :: Python :: 3.10
Classifier: Programming Language :: Python :: 3.11
Classifier: Programming Language :: Python :: 3.12
Classifier: License :: OSI Approved :: MIT License
Classifier: Operating System :: OS Independent
Classifier: Development Status :: 4 - Beta
Classifier: Intended Audience :: Developers
Classifier: Topic :: Software Development :: Libraries :: Python Modules
Classifier: Topic :: Scientific/Engineering :: Artificial Intelligence
Requires-Python: >=3.8
License-File: LICENSE
Requires-Dist: typing-extensions>=4.0.0
Requires-Dist: dataclasses>=0.6; python_version < "3.7"
Provides-Extra: dev
Requires-Dist: pytest>=6.0; extra == "dev"
Requires-Dist: pytest-cov>=2.0; extra == "dev"
Requires-Dist: black>=21.0; extra == "dev"
Requires-Dist: flake8>=3.8; extra == "dev"
Requires-Dist: mypy>=0.800; extra == "dev"
Provides-Extra: docs
Requires-Dist: mkdocs>=1.4; extra == "docs"
Requires-Dist: mkdocs-material>=8.0; extra == "docs"
Dynamic: author
Dynamic: author-email
Dynamic: classifier
Dynamic: description
Dynamic: description-content-type
Dynamic: home-page
Dynamic: keywords
Dynamic: license
Dynamic: license-file
Dynamic: project-url
Dynamic: provides-extra
Dynamic: requires-dist
Dynamic: requires-python
Dynamic: summary
